CdfsunriseDataCollection/_login.py
CdfsunriseDataCollection/_types.py
CdfsunriseDataCollection/collector.py
CdfsunriseDataCollection/goods_analysis/_types.py
CdfsunriseDataCollection/goods_analysis/_utils.py
CdfsunriseDataCollection/goods_analysis/brand.py
CdfsunriseDataCollection/goods_analysis/goods_analysis.py
CdfsunriseDataCollection/goods_analysis/ranking.py
cdfsunrise_data_collection-1.0.4.dist-info/LICENSE
cdfsunrise_data_collection-1.0.4.dist-info/METADATA
cdfsunrise_data_collection-1.0.4.dist-info/WHEEL
cdfsunrise_data_collection-1.0.4.dist-info/RECORD
