Metadata-Version: 2.3
Name: cdfsunrise-data-collection
Version: 1.0.4
Summary: cdfsunrise data collection
License: MIT
Author: martianbugs
Requires-Python: >=3.9,<3.13
Classifier: License :: OSI Approved :: MIT License
Classifier: Programming Language :: Python :: 3
Classifier: Programming Language :: Python :: 3.9
Classifier: Programming Language :: Python :: 3.10
Classifier: Programming Language :: Python :: 3.11
Classifier: Programming Language :: Python :: 3.12
Requires-Dist: browser-automation-launcher (>=1.0.4,<2.0.0)
Requires-Dist: ddddocr (==1.5.6)
